opssection/__init__.py
opssection/fibersection.py
opssection-0.9.0.dist-info/METADATA
opssection-0.9.0.dist-info/WHEEL
opssection-0.9.0.dist-info/licenses/LICENSE
opssection-0.9.0.dist-info/RECORD
