Metadata-Version: 2.1
Name: opssection
Version: 0.9.0
Summary: A package to create openseespy fiber section objects
Author-email: Oktai Alizade Arasi <ok.programss@gmail.com>
License-File: LICENSE
Classifier: License :: OSI Approved :: MIT License
Classifier: Operating System :: Microsoft :: Windows
Classifier: Programming Language :: Python :: 3
Requires-Python: >=3.9
